sqlalchemy_pagination/__init__.py
sqlalchemy_pagination-0.0.2.dist-info/METADATA
sqlalchemy_pagination-0.0.2.dist-info/RECORD
sqlalchemy_pagination-0.0.2.dist-info/WHEEL
sqlalchemy_pagination-0.0.2.dist-info/top_level.txt
